seuratToAdata/__init__.py
seuratToAdata/__pycache__/__init__.cpython-37.pyc
seuratToAdata-0.0.6.data/scripts/seuratToAdata
seuratToAdata-0.0.6.data/scripts/seuratToloom.R
seuratToAdata-0.0.6.dist-info/METADATA
seuratToAdata-0.0.6.dist-info/WHEEL
seuratToAdata-0.0.6.dist-info/top_level.txt
seuratToAdata-0.0.6.dist-info/RECORD
