Metadata-Version: 2.1
Name: seuratToAdata
Version: 0.0.6
Summary: Convert seurat obj to Adata
Home-page: https://jingxinfu.github.io/seuratToAdata
Author: Jingxin Fu
Author-email: jingxinfu.tj@gmail.com
License: UNKNOWN
Keywords: Bioinformatics,Genomics,Computational Biologist
Platform: UNKNOWN
Classifier: Programming Language :: Python
Classifier: License :: OSI Approved :: GNU General Public License v3 or later (GPLv3+)
Classifier: Operating System :: Unix
Classifier: Operating System :: MacOS
Requires-Python: >=3.5
Requires-Dist: scanpy
